README.md
setup.py
kmux/__init__.py
kmux/errors.py
kmux/example.py
kmux/hashutils.py
kmux/jsonutils.py
kmux/limits.py
kmux/models.py
kmux/plugin_aliyun_fc.py
kmux/plugin_bottle.py
kmux/plugin_flask.py
kmux/plugin_tornado.py
kmux/plugin_wsgi.py
kmux/rest.py
kmux.egg-info/PKG-INFO
kmux.egg-info/SOURCES.txt
kmux.egg-info/dependency_links.txt
kmux.egg-info/requires.txt
kmux.egg-info/top_level.txt