Metadata-Version: 2.1
Name: kmux
Version: 0.0.4
Summary: easy for restful development
Home-page: https://gitee.com/muxiaofei/kmux
Author: Mu Xiaofei
Author-email: me@muxiaofei.cn
License: UNKNOWN
Keywords: restful
Platform: UNKNOWN
Classifier: Programming Language :: Python :: 3
Classifier: License :: OSI Approved :: MIT License
Classifier: Operating System :: OS Independent
